{
  "apps": [
    {
      "id": "nord",
      "name": "NordVPN",
      "platforms": {
        "android": {
          "platform": "android",
          "version": "VARY",
          "lastUpdated": "2026-01-19",
          "notes": "• This update may not bring visible changes, and that&#39;s okay. We&#39;ve been tweaking things under the hood to ensure your NordVPN app runs smoother than ever. It&#39;s the invisible work that often makes the biggest difference.",
          "rating": 4.5715218,
          "downloads": "100,000,000+",
          "developer": "Nord Security",
          "url": "https://play.google.com/store/apps/details?id=com.nordvpn.android&hl=en&gl=us",
          "icon": "https://play-lh.googleusercontent.com/zJ3ysMhOnrgMgkxWibuHu_MlzfnpM96mriUfm8f898BMnDFmXa9peQvIaClA3KuBeZk"
        },
        "ios": {
          "platform": "ios",
          "version": "8.60.0",
          "lastUpdated": "2026-01-12",
          "notes": "• A few bugs tried sneaking in. We caught them before they got too cozy.",
          "rating": 4.66462,
          "downloads": "N/A",
          "size": "220990464",
          "developer": "Nordvpn S.A.",
          "url": "https://apps.apple.com/us/app/nordvpn-vpn-fast-secure/id905953485?uo=4",
          "icon": "https://is1-ssl.mzstatic.com/image/thumb/Purple221/v4/22/51/b8/2251b824-df13-c724-361b-471a2da55788/AppIcon-0-0-1x_U007epad-0-1-0-85-220.png/512x512bb.jpg"
        }
      }
    },
    {
      "id": "express",
      "name": "ExpressVPN",
      "platforms": {
        "android": {
          "platform": "android",
          "version": "12.48.0",
          "lastUpdated": "2026-01-16",
          "notes": "Just a minor fix here and there to improve your app experience.",
          "rating": 4.7437367,
          "downloads": "50,000,000+",
          "developer": "ExpressVPN",
          "url": "https://play.google.com/store/apps/details?id=com.expressvpn.vpn&hl=en&gl=us",
          "icon": "https://play-lh.googleusercontent.com/CnGsOmhIKfo1_IAnCUxAYXBaxkJ11rQXqPAGU_t29S6nVsrzTx-3OjMWFf2fk_b7u3g"
        },
        "ios": {
          "platform": "ios",
          "version": "12.40.2",
          "lastUpdated": "2026-01-20",
          "notes": "Just adjusting the sails and making sure the app runs smoothly.",
          "rating": 4.68208,
          "downloads": "N/A",
          "size": "223736832",
          "developer": "Express VPN",
          "url": "https://apps.apple.com/us/app/expressvpn-secure-fast-vpn/id886492891?uo=4",
          "icon": "https://is1-ssl.mzstatic.com/image/thumb/Purple221/v4/2d/f1/3f/2df13fc8-865c-9136-94c6-02fb2077938f/AppIcon-0-1x_U007emarketing-0-8-0-85-220-0.png/512x512bb.jpg"
        }
      }
    },
    {
      "id": "cyberghost",
      "name": "CyberGhost VPN",
      "platforms": {
        "android": {
          "platform": "android",
          "version": "8.32.0.3590",
          "lastUpdated": "2025-09-03",
          "notes": "Hi Ghosties, <br><br>We did some under-the-hood work and chased away bugs to make your VPN experience with us so much smoother. <br><br>There&#39;s more where these goodies came from, so make sure to keep an eye on us. <br><br>Stay safe and secure!",
          "rating": 4.1875,
          "downloads": "10,000,000+",
          "developer": "CyberGhost SRL",
          "url": "https://play.google.com/store/apps/details?id=de.mobileconcepts.cyberghost&hl=en&gl=us",
          "icon": "https://play-lh.googleusercontent.com/mY9EidYNw86nCKpAvQN9DeVOi5iUoCHOSk1pAt-d5WS1UGDkfiooI5Ic3feVbrFvdJI"
        }
      }
    },
    {
      "id": "surfshark",
      "name": "Surfshark VPN",
      "platforms": {
        "android": {
          "platform": "android",
          "version": "3.24.0",
          "lastUpdated": "2026-01-09",
          "notes": "We&#39;ve made a few improvements to enhance the reliability of our ad blocker, Clean Web;<br>Enjoy a smoother VPN with our latest performance and stability fixes.",
          "rating": 4.5980096,
          "downloads": "10,000,000+",
          "developer": "Surfshark B.V.",
          "url": "https://play.google.com/store/apps/details?id=com.surfshark.vpnclient.android&hl=en&gl=us",
          "icon": "https://play-lh.googleusercontent.com/wClkU3TA-rkOFC5dyoYkUjQNSzvxe9URgHn1Q09Kk1tx8piVe4mraaJTmeSKa8ADGRY"
        },
        "ios": {
          "platform": "ios",
          "version": "3.30.0",
          "lastUpdated": "2026-01-19",
          "notes": "- We updated our Products and News tabs to make them more user-friendly and comfortable to navigate.\n- As always, we added a few visual fixes and VPN performance improvements.",
          "rating": 4.72851,
          "downloads": "N/A",
          "size": "583069696",
          "developer": "Surfshark",
          "url": "https://apps.apple.com/us/app/surfshark-vpn-fast-vpn-app/id1391782046?uo=4",
          "icon": "https://is1-ssl.mzstatic.com/image/thumb/Purple221/v4/a2/69/34/a2693417-2cd7-3022-3220-df0c92fca558/iOS_AppIcon-0-0-1x_U007epad-0-0-0-1-0-0-0-85-220.png/512x512bb.jpg"
        }
      }
    },
    {
      "id": "proton",
      "name": "Proton VPN",
      "platforms": {
        "android": {
          "platform": "android",
          "version": "5.15.5.2",
          "lastUpdated": "2026-01-19",
          "notes": "Minor UI and stability improvements",
          "rating": 4.7157245,
          "downloads": "50,000,000+",
          "developer": "Proton AG",
          "url": "https://play.google.com/store/apps/details?id=ch.protonvpn.android&hl=en&gl=us",
          "icon": "https://play-lh.googleusercontent.com/hferjPeJ9_aWi_r5t8L0qOAwU4ZWAyduYmRkYodJOylRKwOxPI_117GzVSkAnhaNOw"
        },
        "ios": {
          "platform": "ios",
          "version": "7.0.1",
          "lastUpdated": "2026-01-14",
          "notes": "- Proton VPN now speaks 26 languages, making the app more accessible to users worldwide.\n- Bug fixes and stability improvements",
          "rating": 4.56738,
          "downloads": "N/A",
          "size": "230630400",
          "developer": "Proton AG",
          "url": "https://apps.apple.com/us/app/proton-vpn-fast-secure/id1437005085?uo=4",
          "icon": "https://is1-ssl.mzstatic.com/image/thumb/Purple221/v4/b5/ab/f0/b5abf083-0a76-ceba-b2cd-931add58c92e/AppIcon-0-0-1x_U007epad-0-1-85-220.png/512x512bb.jpg"
        }
      }
    },
    {
      "id": "tunnelbear",
      "name": "TunnelBear VPN",
      "platforms": {
        "android": {
          "platform": "android",
          "version": "4.8.1",
          "lastUpdated": "2025-12-10",
          "notes": "What’s new in TunnelBear 4.8.1!<br><br>- Paid user experience updated to include exclusive access to country selection and SplitBear.<br>- Under-the-fur improvements.<br>- 21% more bears.",
          "rating": 3.7759187,
          "downloads": "10,000,000+",
          "developer": "TunnelBear, LLC",
          "url": "https://play.google.com/store/apps/details?id=com.tunnelbear.android&hl=en&gl=us",
          "icon": "https://play-lh.googleusercontent.com/3RoSMZTo2xVwcOc23b0EtZXg5KJqQmSkOyf_ab50NoGCE2f97SUNLvSn1SBH2O2bk1tM4MQ455OX4WofVWSp6w"
        },
        "ios": {
          "platform": "ios",
          "version": "4.10.0",
          "lastUpdated": "2026-01-15",
          "notes": "Brushed some fur, under-the-fur improvements, 0.2% new bears added.",
          "rating": 4.67977,
          "downloads": "N/A",
          "size": "125713408",
          "developer": "TunnelBear, LLC",
          "url": "https://apps.apple.com/us/app/tunnelbear-secure-vpn-wifi/id564842283?uo=4",
          "icon": "https://is1-ssl.mzstatic.com/image/thumb/Purple211/v4/6b/b2/3b/6bb23b97-e456-8d85-1776-b4e1daca6949/app-icon-regular-0-0-1x_U007emarketing-0-8-0-85-220.png/512x512bb.jpg"
        }
      }
    },
    {
      "id": "windscribe",
      "name": "Windscribe VPN",
      "platforms": {
        "android": {
          "platform": "android",
          "version": "3.97.1977",
          "lastUpdated": "2025-12-23",
          "notes": "* Improved start up time.<br>* Added Reset password for Sso accounts.<br>* Added back domain for tunnel tests.<br>* Fixed preferred protocol fails to set from change protocol popup.<br>* Fixed IP address overlapping network name.<br>* Fixed disabled Static IP won&#39;t show as disabled in server list.<br>* Fixed Incorrect yearly pricing + discount in Turkey.",
          "rating": 4.689584,
          "downloads": "10,000,000+",
          "developer": "Windscribe",
          "url": "https://play.google.com/store/apps/details?id=com.windscribe.vpn&hl=en&gl=us",
          "icon": "https://play-lh.googleusercontent.com/-LvpTcro1zqQ6YgN_Lx0M51C7wbspNvn4AQza93XxS-d5aV6K8Bq_hdGej3udhAekcs"
        },
        "ios": {
          "platform": "ios",
          "version": "3.9.11",
          "lastUpdated": "2025-12-26",
          "notes": "Release 2025/12/23\n* Fixed an issue where the wrong message could appear when using a voucher\n* Improved reliability of pinned IP connections, including edge cases after reconnecting or signing out\n* Fixed an issue where Static IP connections could switch to Best Location shortly after connecting\n* Added password reset support for accounts created using Sign in with Apple",
          "rating": 4.63841,
          "downloads": "N/A",
          "size": "123686912",
          "developer": "Windscribe Limited",
          "url": "https://apps.apple.com/us/app/vpn-windscribe-fast-secure/id1129435228?uo=4",
          "icon": "https://is1-ssl.mzstatic.com/image/thumb/Purple211/v4/18/7d/e1/187de1b3-c141-002f-cb67-c81fddc75334/AppIcon-0-0-1x_U007epad-0-11-0-0-85-220.png/512x512bb.jpg"
        }
      }
    },
    {
      "id": "urban",
      "name": "Urban VPN",
      "platforms": {
        "android": {
          "platform": "android",
          "version": "1.0.97",
          "lastUpdated": "2025-12-12",
          "notes": "🖥️ Enhanced Protection feature improvements.<br>🔧 Bug fixes - Improved server availability and speed.",
          "rating": 4.3898306,
          "downloads": "10,000,000+",
          "developer": "Urban VPN",
          "url": "https://play.google.com/store/apps/details?id=com.urbanvpn.android&hl=en&gl=us",
          "icon": "https://play-lh.googleusercontent.com/uGBUhlrpfw7FvgUtpgik4FePOhoDrb8N41v3VCt1qWK2mYOZVq32IsxShLH5LRDbeg"
        }
      }
    },
    {
      "id": "pia",
      "name": "Private Internet Access VPN",
      "platforms": {
        "android": {
          "platform": "android",
          "version": "4.0.23",
          "lastUpdated": "2025-12-16",
          "notes": "No update notes available",
          "rating": 4.5194345,
          "downloads": "10,000,000+",
          "developer": "PIA Private Internet Access, Inc",
          "url": "https://play.google.com/store/apps/details?id=com.privateinternetaccess.android&hl=en&gl=us",
          "icon": "https://play-lh.googleusercontent.com/pjak9VEb8yALzrZnL6fAA8DlvR3GDwmyHwXK8kcl3PnUN9Aonr3CMQSnZZ0HzSONDWY"
        },
        "ios": {
          "platform": "ios",
          "version": "3.26.4",
          "lastUpdated": "2026-01-21",
          "notes": "We've improved overall app performance and reliability with fixes for the home screen widget VPN toggle, faster connections on captive WiFi networks (hotels, airports), and general bug fixes.",
          "rating": 4.69015,
          "downloads": "N/A",
          "size": "75615232",
          "developer": "Private Internet Access, Inc.",
          "url": "https://apps.apple.com/us/app/vpn-by-private-internet-access/id955626407?uo=4",
          "icon": "https://is1-ssl.mzstatic.com/image/thumb/Purple211/v4/65/15/b6/6515b664-41a9-e28b-e840-befdb65406b1/AppIcon-0-1x_U007emarketing-0-11-0-85-220-0.png/512x512bb.jpg"
        }
      }
    },
    {
      "id": "mullvad",
      "name": "Mullvad VPN",
      "platforms": {
        "android": {
          "platform": "android",
          "version": "2025.11",
          "lastUpdated": "2025-12-08",
          "notes": "- Fixed crash related to user preferences.",
          "rating": 4.2994013,
          "downloads": "1,000,000+",
          "developer": "Mullvad VPN AB",
          "url": "https://play.google.com/store/apps/details?id=net.mullvad.mullvadvpn&hl=en&gl=us",
          "icon": "https://play-lh.googleusercontent.com/X3V8MJMnYasSOTLeFAN-EX8vKrckT2kxnPSeKRyGEU77pa-PVOjvKSvMdcOhnHX9aEg"
        },
        "ios": {
          "platform": "ios",
          "version": "2025.10",
          "lastUpdated": "2025-12-01",
          "notes": "New location view.\nPort 443/TCP can be used for UDP-over-TCP.",
          "rating": 4.12381,
          "downloads": "N/A",
          "size": "40729600",
          "developer": "Mullvad VPN AB",
          "url": "https://apps.apple.com/us/app/mullvad-vpn/id1488466513?uo=4",
          "icon": "https://is1-ssl.mzstatic.com/image/thumb/Purple221/v4/e8/2e/5a/e82e5a8a-abfc-83ac-4420-2d77512d3368/AppIcon-0-0-1x_U007epad-0-1-0-0-85-220.png/512x512bb.jpg"
        }
      }
    }
  ],
  "feed": [
    {
      "id": "pia_ios",
      "appId": "pia",
      "appName": "Private Internet Access VPN",
      "platform": "ios",
      "version": "3.26.4",
      "lastUpdated": "2026-01-21",
      "notes": "We've improved overall app performance and reliability with fixes for the home screen widget VPN toggle, faster connections on captive WiFi networks (hotels, airports), and general bug fixes.",
      "rating": 4.69015,
      "downloads": "N/A",
      "size": "75615232",
      "developer": "Private Internet Access, Inc.",
      "url": "https://apps.apple.com/us/app/vpn-by-private-internet-access/id955626407?uo=4",
      "icon": "https://is1-ssl.mzstatic.com/image/thumb/Purple211/v4/65/15/b6/6515b664-41a9-e28b-e840-befdb65406b1/AppIcon-0-1x_U007emarketing-0-11-0-85-220-0.png/512x512bb.jpg"
    },
    {
      "id": "express_ios",
      "appId": "express",
      "appName": "ExpressVPN",
      "platform": "ios",
      "version": "12.40.2",
      "lastUpdated": "2026-01-20",
      "notes": "Just adjusting the sails and making sure the app runs smoothly.",
      "rating": 4.68208,
      "downloads": "N/A",
      "size": "223736832",
      "developer": "Express VPN",
      "url": "https://apps.apple.com/us/app/expressvpn-secure-fast-vpn/id886492891?uo=4",
      "icon": "https://is1-ssl.mzstatic.com/image/thumb/Purple221/v4/2d/f1/3f/2df13fc8-865c-9136-94c6-02fb2077938f/AppIcon-0-1x_U007emarketing-0-8-0-85-220-0.png/512x512bb.jpg"
    },
    {
      "id": "nord_android",
      "appId": "nord",
      "appName": "NordVPN",
      "platform": "android",
      "version": "VARY",
      "lastUpdated": "2026-01-19",
      "notes": "• This update may not bring visible changes, and that&#39;s okay. We&#39;ve been tweaking things under the hood to ensure your NordVPN app runs smoother than ever. It&#39;s the invisible work that often makes the biggest difference.",
      "rating": 4.5715218,
      "downloads": "100,000,000+",
      "developer": "Nord Security",
      "url": "https://play.google.com/store/apps/details?id=com.nordvpn.android&hl=en&gl=us",
      "icon": "https://play-lh.googleusercontent.com/zJ3ysMhOnrgMgkxWibuHu_MlzfnpM96mriUfm8f898BMnDFmXa9peQvIaClA3KuBeZk"
    },
    {
      "id": "surfshark_ios",
      "appId": "surfshark",
      "appName": "Surfshark VPN",
      "platform": "ios",
      "version": "3.30.0",
      "lastUpdated": "2026-01-19",
      "notes": "- We updated our Products and News tabs to make them more user-friendly and comfortable to navigate.\n- As always, we added a few visual fixes and VPN performance improvements.",
      "rating": 4.72851,
      "downloads": "N/A",
      "size": "583069696",
      "developer": "Surfshark",
      "url": "https://apps.apple.com/us/app/surfshark-vpn-fast-vpn-app/id1391782046?uo=4",
      "icon": "https://is1-ssl.mzstatic.com/image/thumb/Purple221/v4/a2/69/34/a2693417-2cd7-3022-3220-df0c92fca558/iOS_AppIcon-0-0-1x_U007epad-0-0-0-1-0-0-0-85-220.png/512x512bb.jpg"
    },
    {
      "id": "proton_android",
      "appId": "proton",
      "appName": "Proton VPN",
      "platform": "android",
      "version": "5.15.5.2",
      "lastUpdated": "2026-01-19",
      "notes": "Minor UI and stability improvements",
      "rating": 4.7157245,
      "downloads": "50,000,000+",
      "developer": "Proton AG",
      "url": "https://play.google.com/store/apps/details?id=ch.protonvpn.android&hl=en&gl=us",
      "icon": "https://play-lh.googleusercontent.com/hferjPeJ9_aWi_r5t8L0qOAwU4ZWAyduYmRkYodJOylRKwOxPI_117GzVSkAnhaNOw"
    },
    {
      "id": "express_android",
      "appId": "express",
      "appName": "ExpressVPN",
      "platform": "android",
      "version": "12.48.0",
      "lastUpdated": "2026-01-16",
      "notes": "Just a minor fix here and there to improve your app experience.",
      "rating": 4.7437367,
      "downloads": "50,000,000+",
      "developer": "ExpressVPN",
      "url": "https://play.google.com/store/apps/details?id=com.expressvpn.vpn&hl=en&gl=us",
      "icon": "https://play-lh.googleusercontent.com/CnGsOmhIKfo1_IAnCUxAYXBaxkJ11rQXqPAGU_t29S6nVsrzTx-3OjMWFf2fk_b7u3g"
    },
    {
      "id": "tunnelbear_ios",
      "appId": "tunnelbear",
      "appName": "TunnelBear VPN",
      "platform": "ios",
      "version": "4.10.0",
      "lastUpdated": "2026-01-15",
      "notes": "Brushed some fur, under-the-fur improvements, 0.2% new bears added.",
      "rating": 4.67977,
      "downloads": "N/A",
      "size": "125713408",
      "developer": "TunnelBear, LLC",
      "url": "https://apps.apple.com/us/app/tunnelbear-secure-vpn-wifi/id564842283?uo=4",
      "icon": "https://is1-ssl.mzstatic.com/image/thumb/Purple211/v4/6b/b2/3b/6bb23b97-e456-8d85-1776-b4e1daca6949/app-icon-regular-0-0-1x_U007emarketing-0-8-0-85-220.png/512x512bb.jpg"
    },
    {
      "id": "proton_ios",
      "appId": "proton",
      "appName": "Proton VPN",
      "platform": "ios",
      "version": "7.0.1",
      "lastUpdated": "2026-01-14",
      "notes": "- Proton VPN now speaks 26 languages, making the app more accessible to users worldwide.\n- Bug fixes and stability improvements",
      "rating": 4.56738,
      "downloads": "N/A",
      "size": "230630400",
      "developer": "Proton AG",
      "url": "https://apps.apple.com/us/app/proton-vpn-fast-secure/id1437005085?uo=4",
      "icon": "https://is1-ssl.mzstatic.com/image/thumb/Purple221/v4/b5/ab/f0/b5abf083-0a76-ceba-b2cd-931add58c92e/AppIcon-0-0-1x_U007epad-0-1-85-220.png/512x512bb.jpg"
    },
    {
      "id": "nord_ios",
      "appId": "nord",
      "appName": "NordVPN",
      "platform": "ios",
      "version": "8.60.0",
      "lastUpdated": "2026-01-12",
      "notes": "• A few bugs tried sneaking in. We caught them before they got too cozy.",
      "rating": 4.66462,
      "downloads": "N/A",
      "size": "220990464",
      "developer": "Nordvpn S.A.",
      "url": "https://apps.apple.com/us/app/nordvpn-vpn-fast-secure/id905953485?uo=4",
      "icon": "https://is1-ssl.mzstatic.com/image/thumb/Purple221/v4/22/51/b8/2251b824-df13-c724-361b-471a2da55788/AppIcon-0-0-1x_U007epad-0-1-0-85-220.png/512x512bb.jpg"
    },
    {
      "id": "surfshark_android",
      "appId": "surfshark",
      "appName": "Surfshark VPN",
      "platform": "android",
      "version": "3.24.0",
      "lastUpdated": "2026-01-09",
      "notes": "We&#39;ve made a few improvements to enhance the reliability of our ad blocker, Clean Web;<br>Enjoy a smoother VPN with our latest performance and stability fixes.",
      "rating": 4.5980096,
      "downloads": "10,000,000+",
      "developer": "Surfshark B.V.",
      "url": "https://play.google.com/store/apps/details?id=com.surfshark.vpnclient.android&hl=en&gl=us",
      "icon": "https://play-lh.googleusercontent.com/wClkU3TA-rkOFC5dyoYkUjQNSzvxe9URgHn1Q09Kk1tx8piVe4mraaJTmeSKa8ADGRY"
    },
    {
      "id": "windscribe_ios",
      "appId": "windscribe",
      "appName": "Windscribe VPN",
      "platform": "ios",
      "version": "3.9.11",
      "lastUpdated": "2025-12-26",
      "notes": "Release 2025/12/23\n* Fixed an issue where the wrong message could appear when using a voucher\n* Improved reliability of pinned IP connections, including edge cases after reconnecting or signing out\n* Fixed an issue where Static IP connections could switch to Best Location shortly after connecting\n* Added password reset support for accounts created using Sign in with Apple",
      "rating": 4.63841,
      "downloads": "N/A",
      "size": "123686912",
      "developer": "Windscribe Limited",
      "url": "https://apps.apple.com/us/app/vpn-windscribe-fast-secure/id1129435228?uo=4",
      "icon": "https://is1-ssl.mzstatic.com/image/thumb/Purple211/v4/18/7d/e1/187de1b3-c141-002f-cb67-c81fddc75334/AppIcon-0-0-1x_U007epad-0-11-0-0-85-220.png/512x512bb.jpg"
    },
    {
      "id": "windscribe_android",
      "appId": "windscribe",
      "appName": "Windscribe VPN",
      "platform": "android",
      "version": "3.97.1977",
      "lastUpdated": "2025-12-23",
      "notes": "* Improved start up time.<br>* Added Reset password for Sso accounts.<br>* Added back domain for tunnel tests.<br>* Fixed preferred protocol fails to set from change protocol popup.<br>* Fixed IP address overlapping network name.<br>* Fixed disabled Static IP won&#39;t show as disabled in server list.<br>* Fixed Incorrect yearly pricing + discount in Turkey.",
      "rating": 4.689584,
      "downloads": "10,000,000+",
      "developer": "Windscribe",
      "url": "https://play.google.com/store/apps/details?id=com.windscribe.vpn&hl=en&gl=us",
      "icon": "https://play-lh.googleusercontent.com/-LvpTcro1zqQ6YgN_Lx0M51C7wbspNvn4AQza93XxS-d5aV6K8Bq_hdGej3udhAekcs"
    },
    {
      "id": "pia_android",
      "appId": "pia",
      "appName": "Private Internet Access VPN",
      "platform": "android",
      "version": "4.0.23",
      "lastUpdated": "2025-12-16",
      "notes": "No update notes available",
      "rating": 4.5194345,
      "downloads": "10,000,000+",
      "developer": "PIA Private Internet Access, Inc",
      "url": "https://play.google.com/store/apps/details?id=com.privateinternetaccess.android&hl=en&gl=us",
      "icon": "https://play-lh.googleusercontent.com/pjak9VEb8yALzrZnL6fAA8DlvR3GDwmyHwXK8kcl3PnUN9Aonr3CMQSnZZ0HzSONDWY"
    },
    {
      "id": "urban_android",
      "appId": "urban",
      "appName": "Urban VPN",
      "platform": "android",
      "version": "1.0.97",
      "lastUpdated": "2025-12-12",
      "notes": "🖥️ Enhanced Protection feature improvements.<br>🔧 Bug fixes - Improved server availability and speed.",
      "rating": 4.3898306,
      "downloads": "10,000,000+",
      "developer": "Urban VPN",
      "url": "https://play.google.com/store/apps/details?id=com.urbanvpn.android&hl=en&gl=us",
      "icon": "https://play-lh.googleusercontent.com/uGBUhlrpfw7FvgUtpgik4FePOhoDrb8N41v3VCt1qWK2mYOZVq32IsxShLH5LRDbeg"
    },
    {
      "id": "tunnelbear_android",
      "appId": "tunnelbear",
      "appName": "TunnelBear VPN",
      "platform": "android",
      "version": "4.8.1",
      "lastUpdated": "2025-12-10",
      "notes": "What’s new in TunnelBear 4.8.1!<br><br>- Paid user experience updated to include exclusive access to country selection and SplitBear.<br>- Under-the-fur improvements.<br>- 21% more bears.",
      "rating": 3.7759187,
      "downloads": "10,000,000+",
      "developer": "TunnelBear, LLC",
      "url": "https://play.google.com/store/apps/details?id=com.tunnelbear.android&hl=en&gl=us",
      "icon": "https://play-lh.googleusercontent.com/3RoSMZTo2xVwcOc23b0EtZXg5KJqQmSkOyf_ab50NoGCE2f97SUNLvSn1SBH2O2bk1tM4MQ455OX4WofVWSp6w"
    },
    {
      "id": "mullvad_android",
      "appId": "mullvad",
      "appName": "Mullvad VPN",
      "platform": "android",
      "version": "2025.11",
      "lastUpdated": "2025-12-08",
      "notes": "- Fixed crash related to user preferences.",
      "rating": 4.2994013,
      "downloads": "1,000,000+",
      "developer": "Mullvad VPN AB",
      "url": "https://play.google.com/store/apps/details?id=net.mullvad.mullvadvpn&hl=en&gl=us",
      "icon": "https://play-lh.googleusercontent.com/X3V8MJMnYasSOTLeFAN-EX8vKrckT2kxnPSeKRyGEU77pa-PVOjvKSvMdcOhnHX9aEg"
    },
    {
      "id": "mullvad_ios",
      "appId": "mullvad",
      "appName": "Mullvad VPN",
      "platform": "ios",
      "version": "2025.10",
      "lastUpdated": "2025-12-01",
      "notes": "New location view.\nPort 443/TCP can be used for UDP-over-TCP.",
      "rating": 4.12381,
      "downloads": "N/A",
      "size": "40729600",
      "developer": "Mullvad VPN AB",
      "url": "https://apps.apple.com/us/app/mullvad-vpn/id1488466513?uo=4",
      "icon": "https://is1-ssl.mzstatic.com/image/thumb/Purple221/v4/e8/2e/5a/e82e5a8a-abfc-83ac-4420-2d77512d3368/AppIcon-0-0-1x_U007epad-0-1-0-0-85-220.png/512x512bb.jpg"
    },
    {
      "id": "cyberghost_android",
      "appId": "cyberghost",
      "appName": "CyberGhost VPN",
      "platform": "android",
      "version": "8.32.0.3590",
      "lastUpdated": "2025-09-03",
      "notes": "Hi Ghosties, <br><br>We did some under-the-hood work and chased away bugs to make your VPN experience with us so much smoother. <br><br>There&#39;s more where these goodies came from, so make sure to keep an eye on us. <br><br>Stay safe and secure!",
      "rating": 4.1875,
      "downloads": "10,000,000+",
      "developer": "CyberGhost SRL",
      "url": "https://play.google.com/store/apps/details?id=de.mobileconcepts.cyberghost&hl=en&gl=us",
      "icon": "https://play-lh.googleusercontent.com/mY9EidYNw86nCKpAvQN9DeVOi5iUoCHOSk1pAt-d5WS1UGDkfiooI5Ic3feVbrFvdJI"
    }
  ],
  "stats": {
    "totalApps": 10,
    "recentUpdates": 6,
    "androidApps": 10,
    "iosApps": 8,
    "lastUpdated": "2026-01-22T12:31:19.936Z"
  },
  "appIcons": {
    "nord": "https://is1-ssl.mzstatic.com/image/thumb/Purple221/v4/22/51/b8/2251b824-df13-c724-361b-471a2da55788/AppIcon-0-0-1x_U007epad-0-1-0-85-220.png/512x512bb.jpg",
    "express": "https://is1-ssl.mzstatic.com/image/thumb/Purple221/v4/2d/f1/3f/2df13fc8-865c-9136-94c6-02fb2077938f/AppIcon-0-1x_U007emarketing-0-8-0-85-220-0.png/512x512bb.jpg",
    "cyberghost": "https://play-lh.googleusercontent.com/mY9EidYNw86nCKpAvQN9DeVOi5iUoCHOSk1pAt-d5WS1UGDkfiooI5Ic3feVbrFvdJI",
    "surfshark": "https://is1-ssl.mzstatic.com/image/thumb/Purple221/v4/a2/69/34/a2693417-2cd7-3022-3220-df0c92fca558/iOS_AppIcon-0-0-1x_U007epad-0-0-0-1-0-0-0-85-220.png/512x512bb.jpg",
    "proton": "https://is1-ssl.mzstatic.com/image/thumb/Purple221/v4/b5/ab/f0/b5abf083-0a76-ceba-b2cd-931add58c92e/AppIcon-0-0-1x_U007epad-0-1-85-220.png/512x512bb.jpg",
    "tunnelbear": "https://is1-ssl.mzstatic.com/image/thumb/Purple211/v4/6b/b2/3b/6bb23b97-e456-8d85-1776-b4e1daca6949/app-icon-regular-0-0-1x_U007emarketing-0-8-0-85-220.png/512x512bb.jpg",
    "windscribe": "https://is1-ssl.mzstatic.com/image/thumb/Purple211/v4/18/7d/e1/187de1b3-c141-002f-cb67-c81fddc75334/AppIcon-0-0-1x_U007epad-0-11-0-0-85-220.png/512x512bb.jpg",
    "urban": "https://play-lh.googleusercontent.com/uGBUhlrpfw7FvgUtpgik4FePOhoDrb8N41v3VCt1qWK2mYOZVq32IsxShLH5LRDbeg",
    "pia": "https://is1-ssl.mzstatic.com/image/thumb/Purple211/v4/65/15/b6/6515b664-41a9-e28b-e840-befdb65406b1/AppIcon-0-1x_U007emarketing-0-11-0-85-220-0.png/512x512bb.jpg",
    "mullvad": "https://is1-ssl.mzstatic.com/image/thumb/Purple221/v4/e8/2e/5a/e82e5a8a-abfc-83ac-4420-2d77512d3368/AppIcon-0-0-1x_U007epad-0-1-0-0-85-220.png/512x512bb.jpg"
  },
  "totalApps": 10,
  "metadata": {
    "generatedAt": "2026-01-22T12:31:19.936Z",
    "totalExecutionTime": 30,
    "successfulApps": 10
  }
}